.gitignore
.travis.yml
01-activate-behaviors.png
02-create-microsite.png
03-select-local-skin.png
04-have-local-skin.png
CHANGES.rst
MANIFEST.in
README.rst
bootstrap.py
buildout.cfg
develop.cfg
i18n.sh
setup.py
travis.cfg
docs/tour.robot
src/collective/__init__.py
src/collective.behavior.localskin.egg-info/PKG-INFO
src/collective.behavior.localskin.egg-info/SOURCES.txt
src/collective.behavior.localskin.egg-info/dependency_links.txt
src/collective.behavior.localskin.egg-info/entry_points.txt
src/collective.behavior.localskin.egg-info/namespace_packages.txt
src/collective.behavior.localskin.egg-info/not-zip-safe
src/collective.behavior.localskin.egg-info/requires.txt
src/collective.behavior.localskin.egg-info/top_level.txt
src/collective/behavior/__init__.py
src/collective/behavior/localskin/__init__.py
src/collective/behavior/localskin/behavior.py
src/collective/behavior/localskin/configure.zcml
src/collective/behavior/localskin/testing.py
src/collective/behavior/localskin/locales/collective.behavior.localskin.pot
src/collective/behavior/localskin/locales/manual.pot
src/collective/behavior/localskin/locales/en/LC_MESSAGES/collective.behavior.localskin.mo
src/collective/behavior/localskin/locales/en/LC_MESSAGES/collective.behavior.localskin.po
src/collective/behavior/localskin/locales/fi/LC_MESSAGES/collective.behavior.localskin.mo
src/collective/behavior/localskin/locales/fi/LC_MESSAGES/collective.behavior.localskin.po
src/collective/behavior/localskin/tests/__init__.py
src/collective/behavior/localskin/tests/test_localskin.robot
src/collective/behavior/localskin/tests/test_robot.py