Metadata-Version: 1.0
Name: collective.behavior.localskin
Version: 0.9.2
Summary: Dexterity behavior to enable a local theme skin
Home-page: https://github.com/collective/collective.behavior.localskin/
Author: Asko Soukka
Author-email: asko.soukka@iki.fi
License: GPL
Platform: UNKNOWN
Classifier: Programming Language :: Python
Classifier: Framework :: Plone :: 4.3
